[{"content":"项目介绍 本项目设计基于Python的Flask框架、SQLite数据库、HTML、CSS、Javascript、Bootstrap5框架等成功开发了一个校园墙网站。\n本项目是山东省实验中学（西校区）校园墙网站，于2023年9月至11月历时三个月完成。项目代码已基于MIT开源协议在Gitee和Github开源，开源地址：https://gitee.com/creeper2007/xi-qiang-mit 、 https://github.com/cre0110/XiQiang\n技术路径 后端：Python + Flask框架 数据：SQLite数据库 + Flask-sqlalchemy 前端：Bootstrap5 + HTML/CSS/Javascript\n当时写的研究性学习报告 http://file.lndweb.top/uploads/校园墙项目报告.pdf\n效果截图 ","date":"2025-09-21T17:21:25+08:00","image":"https://cre0110.github.io/p/%E5%85%B3%E4%BA%8E2023%E5%B9%B4%E7%9A%84%E6%A0%A1%E5%9B%AD%E5%A2%99%E9%A1%B9%E7%9B%AE/wall_hu_2d5184bfee3e0470.png","permalink":"https://cre0110.github.io/p/%E5%85%B3%E4%BA%8E2023%E5%B9%B4%E7%9A%84%E6%A0%A1%E5%9B%AD%E5%A2%99%E9%A1%B9%E7%9B%AE/","title":"关于2023年的校园墙项目"},{"content":"B站教程 一些命令行 在本地启动 ./hugo.exe server -D\n创建新网站 ./hugo.exe new site name\n创建新文章 ./hugo.exe new content post/myFirstBlog/index.md\n更新内容（需要重新git） ./hugo.exe -D\n","date":"2025-09-21T15:23:29+08:00","image":"https://cre0110.github.io/p/hugo%E7%9A%84%E5%91%BD%E4%BB%A4%E8%A1%8C/hugo_hu_9f075c2cec7a47c6.png","permalink":"https://cre0110.github.io/p/hugo%E7%9A%84%E5%91%BD%E4%BB%A4%E8%A1%8C/","title":"Hugo的命令行"}]